tutor_contrib_sentry-20.0.0.dist-info/licenses/LICENSE.txt
tutorsentry/__about__.py
tutorsentry/__init__.py
tutorsentry/plugin.py
tutorsentry/patches/.gitignore
tutorsentry/patches/openedx-common-settings
tutorsentry/patches/openedx-dockerfile-post-python-requirements
tutorsentry/patches/uwsgi-config
tutorsentry/templates/sentry/apps/.gitignore
tutorsentry/templates/sentry/build/.gitignore
tutorsentry/templates/sentry/tasks/lms/.gitignore
tutor_contrib_sentry-20.0.0.dist-info/METADATA
tutor_contrib_sentry-20.0.0.dist-info/WHEEL
tutor_contrib_sentry-20.0.0.dist-info/entry_points.txt
tutor_contrib_sentry-20.0.0.dist-info/top_level.txt
tutor_contrib_sentry-20.0.0.dist-info/RECORD
