Metadata-Version: 2.4
Name: tutor-contrib-sentry
Version: 20.0.0
Summary: Sentry Integration for Open edX
Author-email: eduNEXT <technical@edunext.co>
License: AGPLv3
Project-URL: homepage, https://github.com/eduNEXT/tutor-contrib-sentry
Project-URL: repository, https://github.com/eduNEXT/tutor-contrib-sentry
Project-URL: Issue tracker, https://github.com/eduNEXT/tutor-contrib-sentry/issues
Classifier: Development Status :: 3 - Alpha
Classifier: Intended Audience :: Developers
Classifier: License :: OSI Approved :: GNU Affero General Public License v3
Classifier: Operating System :: OS Independent
Classifier: Programming Language :: Python
Classifier: Programming Language :: Python :: 3.9
Classifier: Programming Language :: Python :: 3.10
Classifier: Programming Language :: Python :: 3.11
Classifier: Programming Language :: Python :: 3.12
Requires-Python: >=3.9
License-File: LICENSE.txt
Requires-Dist: tutor~=20.0
Provides-Extra: dev
Requires-Dist: black; extra == "dev"
Requires-Dist: build; extra == "dev"
Requires-Dist: isort; extra == "dev"
Requires-Dist: mypy; extra == "dev"
Requires-Dist: pylint; extra == "dev"
Requires-Dist: python-semantic-release; extra == "dev"
Dynamic: license-file
